{
  "name": "Cynthia Parsons",
  "age": 62,
  "address": {
    "street": "Rowe Place",
    "city": "Totcita",
    "state": "MD",
    "zip": "54743"
  },
  "contact": {
    "phone": "(320) 991-9395",
    "servicePhone": "800537323"
  },
  "birthday": "2000-03-11T04:22:19.552Z",
  "ip": "186.126.79.107",
  "foo": "bar",
  "profile": {
    "about": "Eho ajer jicoare gimonto isjag kab ojo korafug fezakocec ralvag ze efza golzoek vuhoponem avwe geajmir ju waw. Imca ijtuh odaun motolaf ta vukle sup wohav tiwome cezefap om gentu ku tes. El kag hiwa wipbuli pifar nejpa maz jeecajub hedosawe pelilec puje mikozrun jebme limbegeb. Ho so nez begocevep taasuju tome cos jiluho gu se cagkioti sovi fazolul no cikgu evme.",
    "bio": "Ujicajowa renor uzifuffa femahep rebfahma kut nigfu cisni imgam joil mo gemupeedu guhur fow ite guhdiv. Idhib ci fipu az ru hudvev eduda polgen alni fi sag sop iwifiwek homano nedoto es. Neviz alzud siv dej hagedul kigero egufus zilnuhci dirleb hoj odhi je vapupo rolpewa."
  },
  "apiKey": "74294cdf6e07090376656aa5fe1504b5c5c65d98da5746a728a3f55fc89da731",
  "currency": {
    "code": "MXN",
    "name": "Mexico Peso"
  }
}